build/lib/build/lib/whl_env/__init__.py
build/lib/build/lib/whl_env/collector.py
build/lib/build/lib/whl_env/main.py
build/lib/build/lib/whl_env/utils.py
build/lib/build/lib/whl_env/verifier.py
build/lib/build/lib/whl_env/basic/__init__.py
build/lib/build/lib/whl_env/basic/uuid.py
build/lib/build/lib/whl_env/hardware/__init__.py
build/lib/build/lib/whl_env/hardware/misc.py
build/lib/build/lib/whl_env/hardware/sensor.py
build/lib/build/lib/whl_env/hardware/vehicle.py
build/lib/build/lib/whl_env/hardware/compute_unit/__init__.py
build/lib/build/lib/whl_env/hardware/compute_unit/cpu.py
build/lib/build/lib/whl_env/hardware/compute_unit/disk.py
build/lib/build/lib/whl_env/hardware/compute_unit/gpu.py
build/lib/build/lib/whl_env/hardware/compute_unit/memory.py
build/lib/build/lib/whl_env/hardware/compute_unit/network.py
build/lib/build/lib/whl_env/software/__init__.py
build/lib/build/lib/whl_env/software/autopilot.py
build/lib/build/lib/whl_env/software/config.py
build/lib/build/lib/whl_env/software/drivers.py
build/lib/build/lib/whl_env/software/realtime.py
build/lib/build/lib/whl_env/software/system.py
build/lib/build/lib/whl_env/software/time_sync.py
build/lib/whl_env/__init__.py
build/lib/whl_env/collector.py
build/lib/whl_env/main.py
build/lib/whl_env/utils.py
build/lib/whl_env/verifier.py
build/lib/whl_env/basic/__init__.py
build/lib/whl_env/basic/uuid.py
build/lib/whl_env/hardware/__init__.py
build/lib/whl_env/hardware/misc.py
build/lib/whl_env/hardware/sensor.py
build/lib/whl_env/hardware/vehicle.py
build/lib/whl_env/hardware/compute_unit/__init__.py
build/lib/whl_env/hardware/compute_unit/cpu.py
build/lib/whl_env/hardware/compute_unit/disk.py
build/lib/whl_env/hardware/compute_unit/gpu.py
build/lib/whl_env/hardware/compute_unit/memory.py
build/lib/whl_env/hardware/compute_unit/network.py
build/lib/whl_env/software/__init__.py
build/lib/whl_env/software/autopilot.py
build/lib/whl_env/software/config.py
build/lib/whl_env/software/drivers.py
whl_env-0.0.1.dist-info/licenses/LICENSE
whl_env-0.0.1.dist-info/METADATA
whl_env-0.0.1.dist-info/WHEEL
whl_env-0.0.1.dist-info/entry_points.txt
whl_env-0.0.1.dist-info/top_level.txt
whl_env-0.0.1.dist-info/RECORD
