Metadata-Version: 2.4
Name: whl-env
Version: 0.0.1
Summary: wheelos env tool
Author-email: daohu527 <daohu527@gmail.com>
Project-URL: Homepage, https://github.com/wheelos-tools/whl_env
Project-URL: Bug Tracker, https://github.com/wheelos-tools/whl_env/issues
Keywords: whl_env,wheelos
Classifier: Programming Language :: Python :: 3
Classifier: Operating System :: OS Independent
Classifier: Intended Audience :: Developers
Classifier: Topic :: Scientific/Engineering :: GIS
Classifier: Programming Language :: Python :: 3 :: Only
Requires-Python: >=3.6
License-File: LICENSE
Dynamic: license-file
